[
    {
        "id": "women-apparel-sarees-0",
        "title": "Samai Cotton Silk Printed Saree With Unstitched Blouse Piece ( Red )",
        "link": "https://www.snapdeal.com/product/samai-cotton-silk-printed-saree/5188147415061010536",
        "price": 267,
        "image_url": "https://g.sdlcdn.com/imgs/k/z/w/Samai-Cotton-Silk-Printed-Saree-SDL550428072-1-8bc54.jpg?w=220&h=258&sharp=7",
        "discount": "91% Off",
        "category": "women-apparel-sarees",
        "reviews": [],
        "sentiment": null,
        "scraped_at": "2025-08-22T09:38:25.981917"
    },
    {
        "id": "women-apparel-sarees-1",
        "title": "WOVEN STOCK Banarasi Silk Woven Saree With Unstitched Blouse Piece ( Light Blue )",
        "link": "https://www.snapdeal.com/product/woven-stock-banarasi-silk-woven/618922086185",
        "price": 427,
        "image_url": "https://g.sdlcdn.com/imgs/k/6/k/WOVEN-STOCK-Banarasi-Silk-Woven-SDL036872949-1-269a3.jpg?w=220&h=258&sharp=7",
        "discount": "73% Off",
        "category": "women-apparel-sarees",
        "reviews": [],
        "sentiment": null,
        "scraped_at": "2025-08-22T09:38:25.985086"
    },
    {
        "id": "women-apparel-sarees-2",
        "title": "Samai Lycra Embellished Chanderi saree With Unstitched Blouse Piece ( Purple )",
        "link": "https://www.snapdeal.com/product/samai-lycra-embellished-chanderi-saree/625454540482",
        "price": 267,
        "image_url": "https://g.sdlcdn.com/imgs/k/6/6/Samai-Lycra-Embellished-Chanderi-saree-SDL555442360-1-05442.jpg?w=220&h=258&sharp=7",
        "discount": "91% Off",
        "category": "women-apparel-sarees",
        "reviews": [],
        "sentiment": null,
        "scraped_at": "2025-08-22T09:38:25.988134"
    },
    {
        "id": "women-apparel-sarees-3",
        "title": "JASHALFAB Chiffon Embellished Saree With Unstitched Blouse Piece ( Teal )",
        "link": "https://www.snapdeal.com/product/jashalfab-chiffon-embellished-saree-with/650651506497",
        "price": 387,
        "image_url": "https://g.sdlcdn.com/imgs/k/6/l/JASHALFAB-Chiffon-Embellished-Saree-With-SDL033938963-1-9e155.jpg?w=220&h=258&sharp=7",
        "discount": "70% Off",
        "category": "women-apparel-sarees",
        "reviews": [],
        "sentiment": null,
        "scraped_at": "2025-08-22T09:38:25.993943"
    },
    {
        "id": "women-apparel-sarees-4",
        "title": "Bhuwal Fashion Georgette Printed Saree With Unstitched Blouse Piece ( Purple )",
        "link": "https://www.snapdeal.com/product/bhuwal-fashion-pack-of-1/6917529675297312179",
        "price": 371,
        "image_url": null,
        "discount": "88% Off",
        "category": "women-apparel-sarees",
        "reviews": [],
        "sentiment": null,
        "scraped_at": "2025-08-22T09:38:25.998194"
    },
    {
        "id": "women-apparel-sarees-5",
        "title": "Samai Georgette Solid Saree With Unstitched Blouse Piece ( Multicolor6 )",
        "link": "https://www.snapdeal.com/product/samai-georgette-solid-saree-with/6052838575677392432",
        "price": 267,
        "image_url": null,
        "discount": "91% Off",
        "category": "women-apparel-sarees",
        "reviews": [],
        "sentiment": null,
        "scraped_at": "2025-08-22T09:38:26.004336"
    },
    {
        "id": "women-apparel-sarees-6",
        "title": "Today Deal Chiffon Self Design Saree With Unstitched Blouse Piece ( Purple )",
        "link": "https://www.snapdeal.com/product/today-deal-chiffon-self-design/623198060947",
        "price": 273,
        "image_url": null,
        "discount": "91% Off",
        "category": "women-apparel-sarees",
        "reviews": [],
        "sentiment": null,
        "scraped_at": "2025-08-22T09:38:26.009893"
    },
    {
        "id": "women-apparel-sarees-7",
        "title": "Vkaran Lycra Cut Outs Saree With Unstitched Blouse Piece ( Black )",
        "link": "https://www.snapdeal.com/product/vkaran-net-cut-outs-saree/671509742585",
        "price": 254,
        "image_url": null,
        "discount": "92% Off",
        "category": "women-apparel-sarees",
        "reviews": [],
        "sentiment": null,
        "scraped_at": "2025-08-22T09:38:26.027259"
    },
    {
        "id": "women-apparel-sarees-8",
        "title": "Today Deal Chiffon Self Design Saree With Unstitched Blouse Piece ( Green )",
        "link": "https://www.snapdeal.com/product/today-deal-chiffon-self-design/656638675884",
        "price": 273,
        "image_url": null,
        "discount": "91% Off",
        "category": "women-apparel-sarees",
        "reviews": [],
        "sentiment": null,
        "scraped_at": "2025-08-22T09:38:26.053881"
    },
    {
        "id": "women-apparel-sarees-9",
        "title": "JILUDI Georgette Solid Saree With Unstitched Blouse Piece ( Yellow )",
        "link": "https://www.snapdeal.com/product/jiludi-georgette-solid-saree-with/620988195230",
        "price": 319,
        "image_url": null,
        "discount": "79% Off",
        "category": "women-apparel-sarees",
        "reviews": [],
        "sentiment": null,
        "scraped_at": "2025-08-22T09:38:26.065618"
    },
    {
        "id": "women-apparel-sarees-10",
        "title": "Today Deal Chiffon Self Design Saree With Unstitched Blouse Piece ( Blue )",
        "link": "https://www.snapdeal.com/product/today-deal-chiffon-self-design/681385391366",
        "price": 273,
        "image_url": null,
        "discount": "91% Off",
        "category": "women-apparel-sarees",
        "reviews": [],
        "sentiment": null,
        "scraped_at": "2025-08-22T09:38:26.083697"
    },
    {
        "id": "women-apparel-sarees-11",
        "title": "Samai Lycra Embellished Chanderi saree With Unstitched Blouse Piece ( Green )",
        "link": "https://www.snapdeal.com/product/samai-lycra-embellished-chanderi-saree/651498794938",
        "price": 267,
        "image_url": null,
        "discount": "91% Off",
        "category": "women-apparel-sarees",
        "reviews": [],
        "sentiment": null,
        "scraped_at": "2025-08-22T09:38:26.095316"
    },
    {
        "id": "women-apparel-sarees-12",
        "title": "Sadhvi Lycra Solid Saree With Unstitched Blouse Piece ( Black )",
        "link": "https://www.snapdeal.com/product/sadhvi-art-silk-embroidered-saree/667321066765",
        "price": 270,
        "image_url": null,
        "discount": "91% Off",
        "category": "women-apparel-sarees",
        "reviews": [],
        "sentiment": null,
        "scraped_at": "2025-08-22T09:38:26.111402"
    },
    {
        "id": "women-apparel-sarees-13",
        "title": "Samai Lycra Embellished Chanderi saree With Unstitched Blouse Piece ( Black )",
        "link": "https://www.snapdeal.com/product/samai-lycra-embellished-chanderi-saree/619431516888",
        "price": 267,
        "image_url": null,
        "discount": "91% Off",
        "category": "women-apparel-sarees",
        "reviews": [],
        "sentiment": null,
        "scraped_at": "2025-08-22T09:38:26.121418"
    },
    {
        "id": "women-apparel-sarees-14",
        "title": "Fashion Studio Georgette Printed Saree With Unstitched Blouse Piece ( Multicolor )",
        "link": "https://www.snapdeal.com/product/fashion-studio-georgette-printed-saree/682754890396",
        "price": 300,
        "image_url": null,
        "discount": "70% Off",
        "category": "women-apparel-sarees",
        "reviews": [],
        "sentiment": null,
        "scraped_at": "2025-08-22T09:38:26.147419"
    },
    {
        "id": "women-apparel-sarees-15",
        "title": "WOVEN STOCK Banarasi Silk Woven Saree With Unstitched Blouse Piece ( Green )",
        "link": "https://www.snapdeal.com/product/woven-stock-banarasi-silk-woven/624575535217",
        "price": 354,
        "image_url": null,
        "discount": "78% Off",
        "category": "women-apparel-sarees",
        "reviews": [],
        "sentiment": null,
        "scraped_at": "2025-08-22T09:38:26.169244"
    },
    {
        "id": "women-apparel-sarees-16",
        "title": "SIMRISH Lycra Striped Saree With Unstitched Blouse Piece ( Multicolor )",
        "link": "https://www.snapdeal.com/product/simrish-lycra-striped-saree-with/621307711474",
        "price": 288,
        "image_url": null,
        "discount": "71% Off",
        "category": "women-apparel-sarees",
        "reviews": [],
        "sentiment": null,
        "scraped_at": "2025-08-22T09:38:26.180401"
    },
    {
        "id": "women-apparel-sarees-17",
        "title": "Gazal Fashions Banarasi Silk Woven Saree With Unstitched Blouse Piece ( Red )",
        "link": "https://www.snapdeal.com/product/gazal-fashions-pack-of-1/637186136118",
        "price": 361,
        "image_url": null,
        "discount": "88% Off",
        "category": "women-apparel-sarees",
        "reviews": [],
        "sentiment": null,
        "scraped_at": "2025-08-22T09:38:26.185702"
    },
    {
        "id": "women-apparel-sarees-18",
        "title": "WOVEN STOCK Banarasi Silk Woven Saree With Unstitched Blouse Piece ( Purple )",
        "link": "https://www.snapdeal.com/product/woven-stock-banarasi-silk-woven/621106714072",
        "price": 427,
        "image_url": null,
        "discount": "73% Off",
        "category": "women-apparel-sarees",
        "reviews": [],
        "sentiment": null,
        "scraped_at": "2025-08-22T09:38:26.189961"
    },
    {
        "id": "women-apparel-sarees-19",
        "title": "JASHALFAB Chiffon Embellished Saree With Unstitched Blouse Piece ( Pink )",
        "link": "https://www.snapdeal.com/product/jashalfab-chiffon-embellished-saree-with/628099980335",
        "price": 410,
        "image_url": null,
        "discount": "68% Off",
        "category": "women-apparel-sarees",
        "reviews": [],
        "sentiment": null,
        "scraped_at": "2025-08-22T09:38:26.195922"
    }
]